d64/__init__.py
d64/bam.py
d64/basic_file.py
d64/binary_file.py
d64/block.py
d64/d64_bam.py
d64/d64_image.py
d64/d71_bam.py
d64/d71_image.py
d64/d80_d82_bam.py
d64/d80_d82_bam_block.py
d64/d80_image.py
d64/d81_bam.py
d64/d81_bam_block.py
d64/d81_dir_entry.py
d64/d81_image.py
d64/d81_relative_file.py
d64/d82_image.py
d64/dir_entry.py
d64/disk_image.py
d64/dos_image.py
d64/dos_path.py
d64/exceptions.py
d64/file.py
d64/partition.py
d64/path_base.py
d64/relative_file.py
d64/side_sector.py
d64/subdirectory.py
d64/super_side_sector.py
d64/vic20.py
d64/scripts/__init__.py
d64/scripts/d64_edit.py
d64/scripts/d64_format.py
d64/scripts/d64_fsck.py
d64/scripts/d64_shell.py
d64-1.10.dist-info/LICENSE
d64-1.10.dist-info/METADATA
d64-1.10.dist-info/WHEEL
d64-1.10.dist-info/entry_points.txt
d64-1.10.dist-info/top_level.txt
d64-1.10.dist-info/RECORD
